{
    "countries": [
      {"name": "Algeria", "abbreviation": "DZ"},
      {"name": "Angola", "abbreviation": "AO"},
      {"name": "Benin", "abbreviation": "BJ"},
      {"name": "Botswana", "abbreviation": "BW"},
      {"name": "Burkina Faso", "abbreviation": "BF"},
      {"name": "Burundi", "abbreviation": "BI"},
      {"name": "Cabo Verde", "abbreviation": "CV"},
      {"name": "Cameroon", "abbreviation": "CM"},
      {"name": "Central African Republic", "abbreviation": "CF"},
      {"name": "Chad", "abbreviation": "TD"},
      {"name": "Comoros", "abbreviation": "KM"},
      {"name": "Congo", "abbreviation": "CG"},
      {"name": "Djibouti", "abbreviation": "DJ"},
      {"name": "Egypt", "abbreviation": "EG"},
      {"name": "Equatorial Guinea", "abbreviation": "GQ"},
      {"name": "Eritrea", "abbreviation": "ER"},
      {"name": "Eswatini", "abbreviation": "SZ"},
      {"name": "Ethiopia", "abbreviation": "ET"},
      {"name": "Gabon", "abbreviation": "GA"},
      {"name": "Gambia", "abbreviation": "GM"},
      {"name": "Ghana", "abbreviation": "GH"},
      {"name": "Guinea", "abbreviation": "GN"},
      {"name": "Guinea-Bissau", "abbreviation": "GW"},
      {"name": "Ivory Coast", "abbreviation": "CI"},
      {"name": "Kenya", "abbreviation": "KE"},
      {"name": "Lesotho", "abbreviation": "LS"},
      {"name": "Liberia", "abbreviation": "LR"},
      {"name": "Libya", "abbreviation": "LY"},
      {"name": "Madagascar", "abbreviation": "MG"},
      {"name": "Malawi", "abbreviation": "MW"},
      {"name": "Mali", "abbreviation": "ML"},
      {"name": "Mauritania", "abbreviation": "MR"},
      {"name": "Mauritius", "abbreviation": "MU"},
      {"name": "Morocco", "abbreviation": "MA"},
      {"name": "Mozambique", "abbreviation": "MZ"},
      {"name": "Namibia", "abbreviation": "NA"},
      {"name": "Niger", "abbreviation": "NE"},
      {"name": "Nigeria", "abbreviation": "NG"},
      {"name": "Rwanda", "abbreviation": "RW"},
      {"name": "Sao Tome and Principe", "abbreviation": "ST"},
      {"name": "Senegal", "abbreviation": "SN"},
      {"name": "Seychelles", "abbreviation": "SC"},
      {"name": "Sierra Leone", "abbreviation": "SL"},
      {"name": "Somalia", "abbreviation": "SO"},
      {"name": "South Africa", "abbreviation": "ZA"},
      {"name": "South Sudan", "abbreviation": "SS"},
      {"name": "Sudan", "abbreviation": "SD"},
      {"name": "Tanzania", "abbreviation": "TZ"},
      {"name": "Togo", "abbreviation": "TG"},
      {"name": "Tunisia", "abbreviation": "TN"},
      {"name": "Uganda", "abbreviation": "UG"},
      {"name": "Zambia", "abbreviation": "ZM"},
      {"name": "Zimbabwe", "abbreviation": "ZW"}
    ]
  }
  